unmand/__init__.py
unmand-2.1.4.dist-info/licenses/LICENSE
unmand-2.1.4.dist-info/METADATA
unmand-2.1.4.dist-info/WHEEL
unmand-2.1.4.dist-info/top_level.txt
unmand-2.1.4.dist-info/RECORD
