Metadata-Version: 2.4
Name: unmand
Version: 2.1.4
Summary: Helper library for consuming the Unmand API
Home-page: https://github.com/unmand-systems/unmand-python
Author: Josiah Khor
Author-email: josiah.khor@unmand.com
Project-URL: Bug Tracker, https://github.com/unmand-systems/unmand-python/issues
Classifier: Development Status :: 4 - Beta
Classifier: Programming Language :: Python :: 3
Classifier: License :: OSI Approved :: GNU Affero General Public License v3
Classifier: Operating System :: OS Independent
Requires-Python: >=3.11
License-File: LICENSE
Requires-Dist: requests
Dynamic: author
Dynamic: author-email
Dynamic: classifier
Dynamic: description
Dynamic: description-content-type
Dynamic: home-page
Dynamic: license-file
Dynamic: project-url
Dynamic: requires-dist
Dynamic: requires-python
Dynamic: summary
